tracklms_to_qti_results/__init__.py
tracklms_to_qti_results/__main__.py
tracklms_to_qti_results/cli.py
tracklms_to_qti_results/converter.py
tracklms_to_qti_results/version.py
tracklms_to_qti_results-0.2.1.dist-info/licenses/LICENSE
tracklms_to_qti_results-0.2.1.dist-info/METADATA
tracklms_to_qti_results-0.2.1.dist-info/WHEEL
tracklms_to_qti_results-0.2.1.dist-info/entry_points.txt
tracklms_to_qti_results-0.2.1.dist-info/top_level.txt
tracklms_to_qti_results-0.2.1.dist-info/RECORD
