Metadata-Version: 2.4
Name: tracklms-to-qti-results
Version: 0.2.1
Summary: Convert Track LMS exports into QTI 3.0 Results Reporting XML.
Author: metyatech
License-Expression: MIT
Project-URL: Homepage, https://github.com/metyatech/tracklms-to-qti-results
Project-URL: Repository, https://github.com/metyatech/tracklms-to-qti-results
Project-URL: Issues, https://github.com/metyatech/tracklms-to-qti-results/issues
Keywords: tracklms,qti,qti-results
Classifier: Programming Language :: Python :: 3
Classifier: Operating System :: OS Independent
Requires-Python: >=3.11
License-File: LICENSE
Dynamic: license-file
